fast_hangle_levenshtein/__init__.py
fast_hangle_levenshtein/_hangle.py
fast_hangle_levenshtein/_index.py
fast_hangle_levenshtein/_string_distance.py
levenshtein_finder/__init__.py
levenshtein_finder/about.py
levenshtein_finder/distance.py
levenshtein_finder/finder.py
levenshtein_finder/normalizer.py
levenshtein_finder/tokenizer.py
levenshtein_finder-1.0.1.dist-info/METADATA
levenshtein_finder-1.0.1.dist-info/WHEEL
levenshtein_finder-1.0.1.dist-info/top_level.txt
levenshtein_finder-1.0.1.dist-info/RECORD
