Metadata-Version: 2.1
Name: levenshtein-finder
Version: 1.0.1
Summary: find similar word / sentences using levenshtein-distance
Home-page: https://github.com/lovit/levenshtein_finder
Author: lovit
License: UNKNOWN
Platform: UNKNOWN
